pydbmate/__init__.py
pydbmate-0.1.1.dist-info/WHEEL
pydbmate-0.1.1.dist-info/METADATA
pydbmate-0.1.1.dist-info/RECORD
