Metadata-Version: 2.1
Name: pydbmate
Version: 0.1.1
Summary: 
Author: Henrique Leal
Author-email: hm.leal@hotmail.com
Requires-Python: >=3.10,<4.0
Classifier: Programming Language :: Python :: 3
Classifier: Programming Language :: Python :: 3.10
Classifier: Programming Language :: Python :: 3.11
